LICENSE.txt
MANIFEST.in
README.rst
setup.py
docs/changelog.rst
docs/conf.py
docs/examples.rst
docs/index.rst
docs/reference.rst
docs/usermanual.rst
examples/discovery.py
examples/matplotlib_plot_sweep.py
examples/pyqtgraph_plot_block.py
examples/show_i_q.py
examples/simple_read.py
examples/sweep_benchmark.py
examples/twisted_discovery.py
examples/twisted_matplotlib_plot_sweep.py
examples/twisted_show_i_q.py
examples/wsa_measure_noise.py
examples/wsa_peak_find.py
pyrf/__init__.py
pyrf/capture_device.py
pyrf/config.py
pyrf/numpy_util.py
pyrf/sweep_device.py
pyrf/units.py
pyrf/util.py
pyrf/version.py
pyrf/vrt.py
pyrf.egg-info/PKG-INFO
pyrf.egg-info/SOURCES.txt
pyrf.egg-info/dependency_links.txt
pyrf.egg-info/entry_points.txt
pyrf.egg-info/not-zip-safe
pyrf.egg-info/top_level.txt
pyrf/connectors/__init__.py
pyrf/connectors/base.py
pyrf/connectors/blocking.py
pyrf/connectors/twisted_async.py
pyrf/devices/__init__.py
pyrf/devices/keysight.py
pyrf/devices/playback.py
pyrf/devices/thinkrf.py
pyrf/devices/thinkrf_properties.py